{"url":"https:\/\/vortexwebclouds.bitrix24.in\/rest\/223\/fij2hs4zk4rmj30j\/crm.item.update.json","info":{"url":"https:\/\/vortexwebclouds.bitrix24.in\/rest\/223\/fij2hs4zk4rmj30j\/crm.item.update.json","content_type":"application\/json; charset=utf-8","http_code":200,"header_size":1027,"request_size":217,"filetime":-1,"ssl_verify_result":0,"redirect_count":0,"total_time":0.525065,"namelookup_time":0.000435,"connect_time":0.200796,"pretransfer_time":0.212856,"size_upload":58,"size_download":1312,"speed_download":2498,"speed_upload":110,"download_content_length":-1,"upload_content_length":58,"starttransfer_time":0.212859,"redirect_time":0,"redirect_url":"","primary_ip":"52.66.109.148","certinfo":[],"primary_port":443,"local_ip":"193.203.184.45","local_port":62708,"http_version":3,"protocol":2,"ssl_verifyresult":0,"scheme":"HTTPS","appconnect_time_us":413554,"connect_time_us":200796,"namelookup_time_us":435,"pretransfer_time_us":212856,"redirect_time_us":0,"starttransfer_time_us":212859,"total_time_us":525065,"effective_method":"POST"},"params":{"method":"crm.item.update","params":{"entityTypeId":1256,"id":"1","fields":{"ufCrm115ReferralFee":"709"}}},"result":{"result":{"item":{"id":1,"xmlId":"","title":"Reference Application #1","createdBy":223,"updatedBy":223,"movedBy":223,"createdTime":"2024-10-16T09:21:29+03:00","updatedTime":"2024-10-16T15:37:45+03:00","movedTime":"2024-10-16T09:21:29+03:00","categoryId":129,"opened":"N","previousStageId":"","begindate":"2024-10-16T03:00:00+03:00","closedate":"2024-10-23T03:00:00+03:00","companyId":0,"contactId":0,"opportunity":0,"isManualOpportunity":"N","taxValue":0,"currencyId":"AED","opportunityAccount":0,"taxValueAccount":0,"accountCurrencyId":"AED","mycompanyId":1,"sourceId":"CALL","sourceDescription":"","webformId":0,"ufCrm115ClientName":"riyaz","ufCrm115AgentName":"rohan","ufCrm115ProjectName":"spring","ufCrm115UnitNumber":"20","ufCrm115PropertyPrice":200,"ufCrm115GrossCommission":10,"ufCrm115ReferralFee":709,"assignedById":223,"lastActivityBy":223,"lastActivityTime":"2024-10-16T09:21:29+03:00","utmSource":null,"utmMedium":null,"utmCampaign":null,"utmContent":null,"utmTerm":null,"observers":[],"contactIds":[],"entityTypeId":1256}},"time":{"start":1729082690.232195,"finish":1729082690.31301,"duration":0.08081507682800293,"processing":0.05180096626281738,"date_start":"2024-10-16T15:44:50+03:00","date_finish":"2024-10-16T15:44:50+03:00","operating_reset_at":1729083290,"operating":0.5197622776031494}}}