{"url":"https:\/\/vortexwebclouds.bitrix24.in\/rest\/223\/fij2hs4zk4rmj30j\/crm.deal.update.json","info":{"url":"https:\/\/vortexwebclouds.bitrix24.in\/rest\/223\/fij2hs4zk4rmj30j\/crm.deal.update.json","content_type":"application\/json; charset=utf-8","http_code":400,"header_size":730,"request_size":218,"filetime":-1,"ssl_verify_result":0,"redirect_count":0,"total_time":0.613199,"namelookup_time":0.137404,"connect_time":0.2035,"pretransfer_time":0.29465,"size_upload":185,"size_download":64,"speed_download":104,"speed_upload":301,"download_content_length":-1,"upload_content_length":185,"starttransfer_time":0.294654,"redirect_time":0,"redirect_url":"","primary_ip":"52.66.109.148","certinfo":[],"primary_port":443,"local_ip":"192.168.31.219","local_port":62856,"http_version":3,"protocol":2,"ssl_verifyresult":0,"scheme":"HTTPS","appconnect_time_us":294419,"connect_time_us":203500,"namelookup_time_us":137404,"pretransfer_time_us":294650,"redirect_time_us":0,"starttransfer_time_us":294654,"total_time_us":613199},"params":{"method":"crm.deal.update","params":{"id":"","fields":{"AMOUNT":"","CURRENCY_ID":"","NAME":"","DEAL_NUMBER":"","CLIENT":"A","CONTACT_ID":"","PARTICIPANT":"","COMPANY_ID":""}}},"result":{"error":"","error_description":"ID is not defined or invalid."}}